AUTHORS
LICENSE
MANIFEST.in
README.rst
pyproject.toml
requirements.txt
setup.cfg
setup.py
wx_icons_suru/__init__.py
wx_icons_suru.egg-info/PKG-INFO
wx_icons_suru.egg-info/SOURCES.txt
wx_icons_suru.egg-info/dependency_links.txt
wx_icons_suru.egg-info/not-zip-safe
wx_icons_suru.egg-info/requires.txt
wx_icons_suru.egg-info/top_level.txt
wx_icons_suru/Suru/__init__.py
wx_icons_suru/Suru/index.theme
wx_icons_suru/Suru/16x16/actions/dialog-apply.png
wx_icons_suru/Suru/16x16/actions/window-close.png
wx_icons_suru/Suru/16x16/apps/accessories-character-map.png
wx_icons_suru/Suru/16x16/apps/accessories-text-editor.png
wx_icons_suru/Suru/16x16/apps/address-book-app.png
wx_icons_suru/Suru/16x16/apps/amazon-store.png
wx_icons_suru/Suru/16x16/apps/aptdaemon-download.png
wx_icons_suru/Suru/16x16/apps/backups-app.png
wx_icons_suru/Suru/16x16/apps/bluetooth.png
wx_icons_suru/Suru/16x16/apps/calculator-app.png
wx_icons_suru/Suru/16x16/apps/calendar-app.png
wx_icons_suru/Suru/16x16/apps/camera-app.png
wx_icons_suru/Suru/16x16/apps/clock-app.png
wx_icons_suru/Suru/16x16/apps/configurator-app.png
wx_icons_suru/Suru/16x16/apps/disk-usage-app.png
wx_icons_suru/Suru/16x16/apps/disk-utility-app.png
wx_icons_suru/Suru/16x16/apps/documents-app.png
wx_icons_suru/Suru/16x16/apps/docviewer-app.png
wx_icons_suru/Suru/16x16/apps/ebook-reader-app.png
wx_icons_suru/Suru/16x16/apps/error-app.png
wx_icons_suru/Suru/16x16/apps/evince.png
wx_icons_suru/Suru/16x16/apps/extensions.png
wx_icons_suru/Suru/16x16/apps/file-roller.png
wx_icons_suru/Suru/16x16/apps/filemanager-app.png
wx_icons_suru/Suru/16x16/apps/gallery-app.png
wx_icons_suru/Suru/16x16/apps/games-app.png
wx_icons_suru/Suru/16x16/apps/gnome-aisleriot.png
wx_icons_suru/Suru/16x16/apps/gnome-mahjongg.png
wx_icons_suru/Suru/16x16/apps/gnome-mines.png
wx_icons_suru/Suru/16x16/apps/help-app.png
wx_icons_suru/Suru/16x16/apps/image-viewer-app.png
wx_icons_suru/Suru/16x16/apps/jockey.png
wx_icons_suru/Suru/16x16/apps/libreoffice-base.png
wx_icons_suru/Suru/16x16/apps/libreoffice-calc.png
wx_icons_suru/Suru/16x16/apps/libreoffice-draw.png
wx_icons_suru/Suru/16x16/apps/libreoffice-impress.png
wx_icons_suru/Suru/16x16/apps/libreoffice-main.png
