Metadata-Version: 2.1
Name: wx-icons-suru
Version: 0.2.0
Summary: Suru icon theme for wxPython 🐍
Home-page: https://github.com/domdfcoding/custom_wx_icons_suru
Author: Dominic Davis-Foster
Author-email: Dominic Davis-Foster <dominic@davis-foster.co.uk>
License: 
Project-URL: Homepage, https://github.com/domdfcoding/custom_wx_icons_suru
Project-URL: Issue Tracker, https://github.com/domdfcoding/custom_wx_icons_suru/issues
Project-URL: Source Code, https://github.com/domdfcoding/custom_wx_icons_suru
Project-URL: Documentation, https://custom-wx-icons-suru.readthedocs.io/en/latest
Keywords: icons,iconset,suru,wxpython
Platform: Windows
Platform: macOS
Platform: Linux
Classifier: Development Status :: 3 - Alpha
Classifier: Environment :: X11 Applications :: GTK
Classifier: Intended Audience :: Developers
Classifier: License :: OSI Approved :: GNU Lesser General Public License v3 or later (LGPLv3+)
Classifier: Operating System :: OS Independent
Classifier: Operating System :: POSIX :: Linux
Classifier: Programming Language :: Python
Classifier: Programming Language :: Python :: 3 :: Only
Classifier: Programming Language :: Python :: 3.7
Classifier: Programming Language :: Python :: 3.8
Classifier: Programming Language :: Python :: 3.9
Classifier: Programming Language :: Python :: 3.10
Classifier: Programming Language :: Python :: 3.11
Classifier: Programming Language :: Python :: 3.12
Classifier: Programming Language :: Python :: 3.13
Classifier: Programming Language :: Python :: Implementation :: CPython
Classifier: Topic :: Desktop Environment :: Gnome
Classifier: Topic :: Software Development :: Libraries :: Python Modules
Classifier: Topic :: Software Development :: User Interfaces
Requires-Python: >=3.7
License-File: LICENSE
License-File: AUTHORS
